Scrapins/__init__.py
Scrapins/openai.py
Scrapins/scrap.py
Scrapins/utils.py
tests/__init__.py
tests/test_utils.py
Scrapins-0.2.2.dist-info/METADATA
Scrapins-0.2.2.dist-info/WHEEL
Scrapins-0.2.2.dist-info/top_level.txt
Scrapins-0.2.2.dist-info/RECORD
