Metadata-Version: 2.1
Name: Scrapins
Version: 0.2.2
Summary: Une description personnelle pour des outils de Scraping
Home-page: https://github.com/Grimmins/Scrapins
Author: Lùkas K.
Author-email: lukas.koltes@hotmail.fr
Classifier: Programming Language :: Python :: 3
Classifier: License :: OSI Approved :: MIT License
Classifier: Operating System :: OS Independent
Requires-Python: >=3.6
